omega_tx/__init__.py
omega_tx/__main__.py
omega_tx/driver.py
omega_tx/mock.py
omega_tx/test.py
omega_tx-0.2.1.dist-info/LICENSE
omega_tx-0.2.1.dist-info/METADATA
omega_tx-0.2.1.dist-info/WHEEL
omega_tx-0.2.1.dist-info/entry_points.txt
omega_tx-0.2.1.dist-info/top_level.txt
omega_tx-0.2.1.dist-info/RECORD
