Metadata-Version: 2.1
Name: omega-tx
Version: 0.2.1
Summary: Python driver for Omega iTHX-W and iBTHX-W transmitters.
Home-page: https://github.com/numat/omega-tx/
Author: Ross Verploegh, PhD
Author-email: ross@numat-tech.com
License: GPLv2
Platform: UNKNOWN
Classifier: License :: OSI Approved :: GNU General Public License v2 (GPLv2)
Classifier: Development Status :: 2 - Pre-Alpha
Classifier: Natural Language :: English
Classifier: Programming Language :: Python
Classifier: Programming Language :: Python :: 3
Classifier: Programming Language :: Python :: 3.8
Classifier: Programming Language :: Python :: 3.9
Classifier: Topic :: Scientific/Engineering :: Human Machine Interfaces
Requires-Dist: aiohttp (>=3.7.2)
